LICENSE
MANIFEST.in
setup.cfg
setup.py
WingDBG/.winghome
WingDBG/DebugHttpServer.py
WingDBG/ScriptDebugging.py
WingDBG/WingDBG.py
WingDBG/ZopeLogFile.py
WingDBG/__init__.py
WingDBG/config.py
WingDBG/configure.zcml
WingDBG/utils.py
WingDBG.egg-info/PKG-INFO
WingDBG.egg-info/SOURCES.txt
WingDBG.egg-info/dependency_links.txt
WingDBG.egg-info/entry_points.txt
WingDBG.egg-info/not-zip-safe
WingDBG.egg-info/top_level.txt
WingDBG/documentation/wingdbgdocs.html
WingDBG/www/advanced.pt
WingDBG/www/configure.pt
WingDBG/www/connection_trouble_help.pt
WingDBG/www/documentation.pt
WingDBG/www/icon.gif
WingDBG/www/migrate.pt
WingDBG/www/remove.pt
WingDBG/www/status.pt