Metadata-Version: 1.1
Name: WingDBG
Version: 6.0.9
Summary: Zope2 to WingIDE debugging driver
Home-page: http://www.wingware.com/doc/howtos/zope
Author: Wingware
Author-email: support@wingware.com
License: MIT
Keywords: Zope2 WingIDE debug pdb
Platform: UNKNOWN
Classifier: Framework :: Zope2
Classifier: Development Status :: 5 - Production/Stable
Classifier: Topic :: Software Development :: Debuggers
Classifier: Programming Language :: Zope
